.gitignore
.mailmap
.pre-commit-config.yaml
LICENCE
README.rst
pyproject.toml
setup.cfg
setup.py
.github/workflows/comment-bot.yml
.github/workflows/test.yml
examples/.gitignore
examples/demo.ipynb
niftypet/CMakeLists.txt
niftypet/Config.cmake.in
niftypet/__init__.py
niftypet/nipet/CMakeLists.txt
niftypet/nipet/__init__.py
niftypet/nipet/_dist_ver.py
niftypet/nipet/mmraux.py
niftypet/nipet/mmrnorm.py
niftypet/nipet/auxdata/AxialFactorForSpan1.npy
niftypet/nipet/auxdata/RelativeScaleFactors_scatter_axial_ssrTOspan1.f32
niftypet/nipet/auxdata/RelativeScaleFactors_scatter_axial_ssrTOspan11.f32
niftypet/nipet/img/__init__.py
niftypet/nipet/img/auximg.py
niftypet/nipet/img/mmrimg.py
niftypet/nipet/img/pipe.py
niftypet/nipet/include/auxmath.h
niftypet/nipet/include/def.h
niftypet/nipet/include/scanner_0.h
niftypet/nipet/lm/CMakeLists.txt
niftypet/nipet/lm/__init__.py
niftypet/nipet/lm/mmrhist.py
niftypet/nipet/lm/pviews.py
niftypet/nipet/lm/src/hst.cu
niftypet/nipet/lm/src/hst.h
niftypet/nipet/lm/src/lm_module.cu
niftypet/nipet/lm/src/lmaux.cu
niftypet/nipet/lm/src/lmaux.h
niftypet/nipet/lm/src/lmproc.cu
niftypet/nipet/lm/src/lmproc.h
niftypet/nipet/lm/src/rnd.cu
niftypet/nipet/lm/src/rnd.h
niftypet/nipet/prj/CMakeLists.txt
niftypet/nipet/prj/__init__.py
niftypet/nipet/prj/mmrprj.py
niftypet/nipet/prj/mmrrec.py
niftypet/nipet/prj/mmrsim.py
niftypet/nipet/prj/src/prj_module.cu
niftypet/nipet/prj/src/prjb.cu
niftypet/nipet/prj/src/prjb.h
niftypet/nipet/prj/src/prjf.cu
niftypet/nipet/prj/src/prjf.h
niftypet/nipet/prj/src/recon.cu
niftypet/nipet/prj/src/recon.h
niftypet/nipet/prj/src/tprj.cu
niftypet/nipet/prj/src/tprj.h
niftypet/nipet/sct/CMakeLists.txt
niftypet/nipet/sct/__init__.py
niftypet/nipet/sct/mmrsct.py
niftypet/nipet/sct/src/ray.cu
niftypet/nipet/sct/src/ray.h
niftypet/nipet/sct/src/sct.cu
niftypet/nipet/sct/src/sct.h
niftypet/nipet/sct/src/sct_module.cu
niftypet/nipet/sct/src/sctaux.cu
niftypet/nipet/sct/src/sctaux.h
niftypet/nipet/src/aux_module.cu
nipet.egg-info/PKG-INFO
nipet.egg-info/SOURCES.txt
nipet.egg-info/dependency_links.txt
nipet.egg-info/not-zip-safe
nipet.egg-info/requires.txt
nipet.egg-info/top_level.txt
