Metadata-Version: 2.1
Name: nipet
Version: 2.2.0
Summary: CUDA-accelerated Python utilities for high-throughput PET/MR image reconstruction and analysis
Home-page: https://github.com/NiftyPET/NIPET
Author: Pawel Markiewicz
Author-email: p.markiewicz@ucl.ac.uk
Maintainer: Casper da Costa-Luis
Maintainer-email: casper.dcl@physics.org
License: Apache 2.0
Project-URL: Changelog, https://github.com/NiftyPET/NIPET/releases
Project-URL: Documentation, https://niftypet.readthedocs.io
Keywords: PET,image reconstruction,analysis
Classifier: Development Status :: 5 - Production/Stable
Classifier: Environment :: GPU
Classifier: Environment :: GPU :: NVIDIA CUDA
Classifier: Intended Audience :: Education
Classifier: Intended Audience :: Healthcare Industry
Classifier: Intended Audience :: Science/Research
Classifier: License :: OSI Approved :: Apache Software License
Classifier: Operating System :: Microsoft :: Windows
Classifier: Operating System :: POSIX :: Linux
Classifier: Programming Language :: C
Classifier: Programming Language :: C++
Classifier: Programming Language :: Python :: 3
Classifier: Programming Language :: Python :: 3.6
Classifier: Programming Language :: Python :: 3.7
Classifier: Programming Language :: Python :: 3.8
Classifier: Programming Language :: Python :: 3.9
Classifier: Programming Language :: Python :: 3.10
Classifier: Programming Language :: Python :: 3 :: Only
Classifier: Topic :: Scientific/Engineering :: Medical Science Apps.
Requires-Python: >=3.6
Provides-Extra: dev
Provides-Extra: examples
License-File: LICENCE
